CE312/compteur16.vhd
LIBRARY IEEE;
USE IEEE.STD_LOGIC_1164.ALL;
USE IEEE.NUMERIC_STD.ALL;
-- use IEEE.STD_LOGIC_ARITH.ALL;

ENTITY compteur_16 IS
    PORT (
        clk : IN STD_LOGIC;
        rst : IN STD_LOGIC;
        enable : IN STD_LOGIC;
        deb : OUT STD_LOGIC;
        out_count : OUT STD_LOGIC_VECTOR (3 DOWNTO 0)
    );
END compteur_16;

ARCHITECTURE modulo_16 OF compteur_16 IS
    SIGNAL t_count : STD_LOGIC_VECTOR(3 DOWNTO 0);
BEGIN
    PROCESS (clk, rst)

    BEGIN
        IF (clk'event AND clk = '1') THEN
            IF rst = '1' THEN
                t_count <= "0000";
            ELSIF enable = '1' THEN
                IF t_count = "1111" THEN
                    t_count <= "0000";
                    deb <= '1';
                ELSE
                    t_count <= std_logic_vector(unsigned(t_count) + 1);
                    deb <= '0';
                END IF;
            END IF;
        END IF;
    END PROCESS;
    out_count <= t_count;
END modulo_16;

3AS1/CE312/TP1/compteur_16_tb.vhd
-- Testbench automatically generated online
-- at https://vhdl.lapinoo.net
-- Generation date : 8.10.2022 11:23:53 UTC

library ieee;
use ieee.std_logic_1164.all;

entity compteur_16_tb is
end compteur_16_tb;

architecture tb of compteur_16_tb is

    component compteur_16
        port (clk       : in std_logic;
              rst       : in std_logic;
              enable    : in std_logic;
              deb       : out std_logic;
              out_count : out std_logic_vector (3 downto 0));
    end component;

    signal clk       : std_logic;
    signal rst       : std_logic;
    signal enable    : std_logic;
    signal deb       : std_logic;
    signal out_count : std_logic_vector (3 downto 0);

    constant TbPeriod : time := 10 ns; -- EDIT Put right period here
    signal TbClock : std_logic := '0';
    signal TbSimEnded : std_logic := '0';

begin

    dut : compteur_16
    port map (clk       => clk,
              rst       => rst,
              enable    => enable,
              deb       => deb,
              out_count => out_count);

    -- Clock generation
    TbClock <= not TbClock after TbPeriod/2 when TbSimEnded /= '1' else '0';

    -- EDIT: Check that clk is really your main clock signal
    clk <= TbClock;

    stimuli : process
    begin
        -- EDIT Adapt initialization as needed
        enable <= '0';

        -- Reset generation
        -- EDIT: Check that rst is really your reset signal
        rst <= '1';
        wait for 100 ns;
        rst <= '0';
        wait for 100 ns;
        enable <= '1';

        -- EDIT Add stimuli here
        wait for 100 * TbPeriod/2;
        rst <= '1';
        wait for 100 ns;
        rst <= '0';
        wait for 100 * TbPeriod/2;

        -- Stop the clock and hence terminate the simulation
        TbSimEnded <= '1';
        wait;
    end process;

end tb;

-- Configuration block below is required by some simulators. Usually no need to edit.

configuration cfg_compteur_16_tb of compteur_16_tb is
    for tb
    end for;
end cfg_compteur_16_tb;

3AS1/CE312/TP1/compteur_16_tb.vcd
$date
  Sat Oct  8 14:20:51 2022
$end
$version
  GHDL v0
$end
$timescale
  1 fs
$end
$scope module standard $end
$upscope $end
$scope module std_logic_1164 $end
$upscope $end
$scope module numeric_std $end
$upscope $end
$scope module compteur_16_tb $end
$var reg 1 ! clk $end
$var reg 1 " rst $end
$var reg 1 # enable $end
$var reg 1 $ deb $end
$var reg 4 % out_count[3:0] $end
$var reg 1 & tbclock $end
$var reg 1 ' tbsimended $end
$scope module dut $end
$var reg 1 ( clk $end
$var reg 1 ) rst $end
$var reg 1 * enable $end
$var reg 1 + deb $end
$var reg 4 , out_count[3:0] $end
$var reg 4 - t_count[3:0] $end
$upscope $end
$upscope $end
$enddefinitions $end
#0
0!
1"
0#
U$
bUUUU %
0&
0'
0(
1)
0*
U+
bUUUU ,
bUUUU -
#5000000
1!
b0000 %
1&
1(
b0000 ,
b0000 -
#10000000
0!
0&
0(
#15000000
1!
1&
1(
#20000000
0!
0&
0(
#25000000
1!
1&
1(
#30000000
0!
0&
0(
#35000000
1!
1&
1(
#40000000
0!
0&
0(
#45000000
1!
1&
1(
#50000000
0!
0&
0(
#55000000
1!
1&
1(
#60000000
0!
0&
0(
#65000000
1!
1&
1(
#70000000
0!
0&
0(
#75000000
1!
1&
1(
#80000000
0!
0&
0(
#85000000
1!
1&
1(
#90000000
0!
0&
0(
#95000000
1!
1&
1(
#100000000
0!
0"
0&
0(
0)
#105000000
1!
1&
1(
#110000000
0!
0&
0(
#115000000
1!
1&
1(
#120000000
0!
0&
0(
#125000000
1!
1&
1(
#130000000
0!
0&
0(
#135000000
1!
1&
1(
#140000000
0!
0&
0(
#145000000
1!
1&
1(
#150000000
0!
0&
0(
#155000000
1!
1&
1(
#160000000
0!
0&
0(
#165000000
1!
1&
1(
#170000000
0!
0&
0(
#175000000
1!
1&
1(
#180000000
0!
0&
0(
#185000000
1!
1&
1(
#190000000
0!
0&
0(
#195000000
1!
1&
1(
#200000000
0!
1#
0&
0(
1*
#205000000
1!
0$
b0001 %
1&
1(
0+
b0001 ,
b0001 -
#210000000
0!
0&
0(
#215000000
1!
b0010 %
1&
1(
b0010 ,
b0010 -
#220000000
0!
0&
0(
#225000000
1!
b0011 %
1&
1(
b0011 ,
b0011 -
#230000000
0!
0&
0(
#235000000
1!
b0100 %
1&
1(
b0100 ,
b0100 -
#240000000
0!
0&
0(
#245000000
1!
b0101 %
1&
1(
b0101 ,
b0101 -
#250000000
0!
0&
0(
#255000000
1!
b0110 %
1&
1(
b0110 ,
b0110 -
#260000000
0!
0&
0(
#265000000
1!
b0111 %
1&
1(
b0111 ,
b0111 -
#270000000
0!
0&
0(
#275000000
1!
b1000 %
1&
1(
b1000 ,
b1000 -
#280000000
0!
0&
0(
#285000000
1!
b1001 %
1&
1(
b1001 ,
b1001 -
#290000000
0!
0&
0(
#295000000
1!
b1010 %
1&
1(
b1010 ,
b1010 -
#300000000
0!
0&
0(
#305000000
1!
b1011 %
1&
1(
b1011 ,
b1011 -
#310000000
0!
0&
0(
#315000000
1!
b1100 %
1&
1(
b1100 ,
b1100 -
#320000000
0!
0&
0(
#325000000
1!
b1101 %
1&
1(
b1101 ,
b1101 -
#330000000
0!
0&
0(
#335000000
1!
b1110 %
1&
1(
b1110 ,
b1110 -
#340000000
0!
0&
0(
#345000000
1!
b1111 %
1&
1(
b1111 ,
b1111 -
#350000000
0!
0&
0(
#355000000
1!
1$
b0000 %
1&
1(
1+
b0000 ,
b0000 -
#360000000
0!
0&
0(
#365000000
1!
0$
b0001 %
1&
1(
0+
b0001 ,
b0001 -
#370000000
0!
0&
0(
#375000000
1!
b0010 %
1&
1(
b0010 ,
b0010 -
#380000000
0!
0&
0(
#385000000
1!
b0011 %
1&
1(
b0011 ,
b0011 -
#390000000
0!
0&
0(
#395000000
1!
b0100 %
1&
1(
b0100 ,
b0100 -
#400000000
0!
0&
0(
#405000000
1!
b0101 %
1&
1(
b0101 ,
b0101 -
#410000000
0!
0&
0(
#415000000
1!
b0110 %
1&
1(
b0110 ,
b0110 -
#420000000
0!
0&
0(
#425000000
1!
b0111 %
1&
1(
b0111 ,
b0111 -
#430000000
0!
0&
0(
#435000000
1!
b1000 %
1&
1(
b1000 ,
b1000 -
#440000000
0!
0&
0(
#445000000
1!
b1001 %
1&
1(
b1001 ,
b1001 -
#450000000
0!
0&
0(
#455000000
1!
b1010 %
1&
1(
b1010 ,
b1010 -
#460000000
0!
0&
0(
#465000000
1!
b1011 %
1&
1(
b1011 ,
b1011 -
#470000000
0!
0&
0(
#475000000
1!
b1100 %
1&
1(
b1100 ,
b1100 -
#480000000
0!
0&
0(
#485000000
1!
b1101 %
1&
1(
b1101 ,
b1101 -
#490000000
0!
0&
0(
#495000000
1!
b1110 %
1&
1(
b1110 ,
b1110 -
#500000000
0!
0&
0(
#505000000
1!
b1111 %
1&
1(
b1111 ,
b1111 -
#510000000
0!
0&
0(
#515000000
1!
1$
b0000 %
1&
1(
1+
b0000 ,
b0000 -
#520000000
0!
0&
0(
#525000000
1!
0$
b0001 %
1&
1(
0+
b0001 ,
b0001 -
#530000000
0!
0&
0(
#535000000
1!
b0010 %
1&
1(
b0010 ,
b0010 -
#540000000
0!
0&
0(
#545000000
1!
b0011 %
1&
1(
b0011 ,
b0011 -
#550000000
0!
0&
0(
#555000000
1!
b0100 %
1&
1(
b0100 ,
b0100 -
#560000000
0!
0&
0(
#565000000
1!
b0101 %
1&
1(
b0101 ,
b0101 -
#570000000
0!
0&
0(
#575000000
1!
b0110 %
1&
1(
b0110 ,
b0110 -
#580000000
0!
0&
0(
#585000000
1!
b0111 %
1&
1(
b0111 ,
b0111 -
#590000000
0!
0&
0(
#595000000
1!
b1000 %
1&
1(
b1000 ,
b1000 -
#600000000
0!
0&
0(
#605000000
1!
b1001 %
1&
1(
b1001 ,
b1001 -
#610000000
0!
0&
0(
#615000000
1!
b1010 %
1&
1(
b1010 ,
b1010 -
#620000000
0!
0&
0(
#625000000
1!
b1011 %
1&
1(
b1011 ,
b1011 -
#630000000
0!
0&
0(
#635000000
1!
b1100 %
1&
1(
b1100 ,
b1100 -
#640000000
0!
0&
0(
#645000000
1!
b1101 %
1&
1(
b1101 ,
b1101 -
#650000000
0!
0&
0(
#655000000
1!
b1110 %
1&
1(
b1110 ,
b1110 -
#660000000
0!
0&
0(
#665000000
1!
b1111 %
1&
1(
b1111 ,
b1111 -
#670000000
0!
0&
0(
#675000000
1!
1$
b0000 %
1&
1(
1+
b0000 ,
b0000 -
#680000000
0!
0&
0(
#685000000
1!
0$
b0001 %
1&
1(
0+
b0001 ,
b0001 -
#690000000
0!
0&
0(
#695000000
1!
b0010 %
1&
1(
b0010 ,
b0010 -
#700000000
0!
1"
0&
0(
1)
#705000000
1!
b0000 %
1&
1(
b0000 ,
b0000 -
#710000000
0!
0&
0(
#715000000
1!
1&
1(
#720000000
0!
0&
0(
#725000000
1!
1&
1(
#730000000
0!
0&
0(
#735000000
1!
1&
1(
#740000000
0!
0&
0(
#745000000
1!
1&
1(
#750000000
0!
0&
0(
#755000000
1!
1&
1(
#760000000
0!
0&
0(
#765000000
1!
1&
1(
#770000000
0!
0&
0(
#775000000
1!
1&
1(
#780000000
0!
0&
0(
#785000000
1!
1&
1(
#790000000
0!
0&
0(
#795000000
1!
1&
1(
#800000000
0!
0"
0&
0(
0)
#805000000
1!
b0001 %
1&
1(
b0001 ,
b0001 -
#810000000
0!
0&
0(
#815000000
1!
b0010 %
1&
1(
b0010 ,
b0010 -
#820000000
0!
0&
0(
#825000000
1!
b0011 %
1&
1(
b0011 ,
b0011 -
#830000000
0!
0&
0(
#835000000
1!
b0100 %
1&
1(
b0100 ,
b0100 -
#840000000
0!
0&
0(
#845000000
1!
b0101 %
1&
1(
b0101 ,
b0101 -
#850000000
0!
0&
0(
#855000000
1!
b0110 %
1&
1(
b0110 ,
b0110 -
#860000000
0!
0&
0(
#865000000
1!
b0111 %
1&
1(
b0111 ,
b0111 -
#870000000
0!
0&
0(
#875000000
1!
b1000 %
1&
1(
b1000 ,
b1000 -
#880000000
0!
0&
0(
#885000000
1!
b1001 %
1&
1(
b1001 ,
b1001 -
#890000000
0!
0&
0(
#895000000
1!
b1010 %
1&
1(
b1010 ,
b1010 -
#900000000
0!
0&
0(
#905000000
1!
b1011 %
1&
1(
b1011 ,
b1011 -
#910000000
0!
0&
0(
#915000000
1!
b1100 %
1&
1(
b1100 ,
b1100 -
#920000000
0!
0&
0(
#925000000
1!
b1101 %
1&
1(
b1101 ,
b1101 -
#930000000
0!
0&
0(
#935000000
1!
b1110 %
1&
1(
b1110 ,
b1110 -
#940000000
0!
0&
0(
#945000000
1!
b1111 %
1&
1(
b1111 ,
b1111 -
#950000000
0!
0&
0(
#955000000
1!
1$
b0000 %
1&
1(
1+
b0000 ,
b0000 -
#960000000
0!
0&
0(
#965000000
1!
0$
b0001 %
1&
1(
0+
b0001 ,
b0001 -
#970000000
0!
0&
0(
#975000000
1!
b0010 %
1&
1(
b0010 ,
b0010 -
#980000000
0!
0&
0(
#985000000
1!
b0011 %
1&
1(
b0011 ,
b0011 -
#990000000
0!
0&
0(
#995000000
1!
b0100 %
1&
1(
b0100 ,
b0100 -
#1000000000
0!
0&
0(
#1005000000
1!
b0101 %
1&
1(
b0101 ,
b0101 -
#1010000000
0!
0&
0(
#1015000000
1!
b0110 %
1&
1(
b0110 ,
b0110 -
#1020000000
0!
0&
0(
#1025000000
1!
b0111 %
1&
1(
b0111 ,
b0111 -
#1030000000
0!
0&
0(
#1035000000
1!
b1000 %
1&
1(
b1000 ,
b1000 -
#1040000000
0!
0&
0(
#1045000000
1!
b1001 %
1&
1(
b1001 ,
b1001 -
#1050000000
0!
0&
0(
#1055000000
1!
b1010 %
1&
1(
b1010 ,
b1010 -
#1060000000
0!
0&
0(
#1065000000
1!
b1011 %
1&
1(
b1011 ,
b1011 -
#1070000000
0!
0&
0(
#1075000000
1!
b1100 %
1&
1(
b1100 ,
b1100 -
#1080000000
0!
0&
0(
#1085000000
1!
b1101 %
1&
1(
b1101 ,
b1101 -
#1090000000
0!
0&
0(
#1095000000
1!
b1110 %
1&
1(
b1110 ,
b1110 -
#1100000000
0!
0&
0(
#1105000000
1!
b1111 %
1&
1(
b1111 ,
b1111 -
#1110000000
0!
0&
0(
#1115000000
1!
1$
b0000 %
1&
1(
1+
b0000 ,
b0000 -
#1120000000
0!
0&
0(
#1125000000
1!
0$
b0001 %
1&
1(
0+
b0001 ,
b0001 -
#1130000000
0!
0&
0(
#1135000000
1!
b0010 %
1&
1(
b0010 ,
b0010 -
#1140000000
0!
0&
0(
#1145000000
1!
b0011 %
1&
1(
b0011 ,
b0011 -
#1150000000
0!
0&
0(
#1155000000
1!
b0100 %
1&
1(
b0100 ,
b0100 -
#1160000000
0!
0&
0(
#1165000000
1!
b0101 %
1&
1(
b0101 ,
b0101 -
#1170000000
0!
0&
0(
#1175000000
1!
b0110 %
1&
1(
b0110 ,
b0110 -
#1180000000
0!
0&
0(
#1185000000
1!
b0111 %
1&
1(
b0111 ,
b0111 -
#1190000000
0!
0&
0(
#1195000000
1!
b1000 %
1&
1(
b1000 ,
b1000 -
#1200000000
0!
0&
0(
#1205000000
1!
b1001 %
1&
1(
b1001 ,
b1001 -
#1210000000
0!
0&
0(
#1215000000
1!
b1010 %
1&
1(
b1010 ,
b1010 -
#1220000000
0!
0&
0(
#1225000000
1!
b1011 %
1&
1(
b1011 ,
b1011 -
#1230000000
0!
0&
0(
#1235000000
1!
b1100 %
1&
1(
b1100 ,
b1100 -
#1240000000
0!
0&
0(
#1245000000
1!
b1101 %
1&
1(
b1101 ,
b1101 -
#1250000000
0!
0&
0(
#1255000000
1!
b1110 %
1&
1(
b1110 ,
b1110 -
#1260000000
0!
0&
0(
#1265000000
1!
b1111 %
1&
1(
b1111 ,
b1111 -
#1270000000
0!
0&
0(
#1275000000
1!
1$
b0000 %
1&
1(
1+
b0000 ,
b0000 -
#1280000000
0!
0&
0(
#1285000000
1!
0$
b0001 %
1&
1(
0+
b0001 ,
b0001 -
#1290000000
0!
0&
0(
#1295000000
1!
b0010 %
1&
1(
b0010 ,
b0010 -
#1300000000
0!
0&
1'
0(
